jmeter_server.py
main.py
analyzer/__init__.py
analyzer/analyzer.py
analyzer/models.py
analyzer/bottleneck/__init__.py
analyzer/bottleneck/analyzer.py
analyzer/insights/__init__.py
analyzer/insights/generator.py
analyzer/mcp/__init__.py
analyzer/metrics/__init__.py
analyzer/metrics/calculator.py
analyzer/parser/__init__.py
analyzer/parser/base.py
analyzer/parser/csv_parser.py
analyzer/parser/xml_parser.py
analyzer/visualization/__init__.py
analyzer/visualization/engine.py
iflow_mcp_qainsights_jmeter_mcp_server-0.1.0.dist-info/METADATA
iflow_mcp_qainsights_jmeter_mcp_server-0.1.0.dist-info/WHEEL
iflow_mcp_qainsights_jmeter_mcp_server-0.1.0.dist-info/entry_points.txt
iflow_mcp_qainsights_jmeter_mcp_server-0.1.0.dist-info/RECORD
