Metadata-Version: 2.4
Name: iflow-mcp_qainsights_jmeter-mcp-server
Version: 0.1.0
Summary: JMeter MCP Server
Requires-Python: >=3.13
Requires-Dist: httpx>=0.28.1
Requires-Dist: mcp[cli]>=1.6.0
Requires-Dist: python-dotenv>=1.0.0
